<?xml version="1.0" encoding="UTF-8" standalone="yes"?>
<operation operationType="ADDITION">
    <firstArgument xmlns:xsi="http://www.w3.org/2001/XMLSchema-instance" xsi:type="variable">
        <name>x</name>
    </firstArgument>
    <secondArgument xmlns:xsi="http://www.w3.org/2001/XMLSchema-instance" xsi:type="operation" operationType="DIVISION">
        <firstArgument xsi:type="operation" operationType="POW">
            <firstArgument xsi:type="variable">
                <name>x</name>
            </firstArgument>
            <secondArgument xsi:type="variable">
                <value>2</value>
            </secondArgument>
        </firstArgument>
        <secondArgument xsi:type="variable">
            <value>2</value>
        </secondArgument>
    </secondArgument>
</operation>
